LICENSE
MANIFEST.in
README.rst
VERSION
requirements.txt
setup.py
introspect/__init__.py
introspect/introspect.py
introspect/window_title.py
introspect.egg-info/PKG-INFO
introspect.egg-info/SOURCES.txt
introspect.egg-info/dependency_links.txt
introspect.egg-info/entry_points.txt
introspect.egg-info/requires.txt
introspect.egg-info/top_level.txt
introspect/scripts/osx_active_window_title.osascript