Metadata-Version: 1.0
Name: introspect
Version: 0.0.0
Summary: how do you spend your time?
Home-page: https://github.com/charlesthomas/introspect
Author: Charles Thomas
Author-email: ch@rlesthom.as
License: The MIT License (MIT)
